Metadata-Version: 1.0
Name: is-taken
Version: 0.1.4
Summary: Check if a PyPI package name is taken.
Home-page: https://github.com/Frederick-S/is-taken
Author: UNKNOWN
Author-email: UNKNOWN
License: UNKNOWN
Platform: UNKNOWN
